amapy_contents/__init__.py
amapy_contents/blobstore_content.py
amapy_contents/content.py
amapy_contents/content_factory.py
amapy_contents/content_set.py
amapy_contents/content_stat.py
amapy_contents/content_state.py
amapy_contents/content_uploader.py
amapy_contents/db_content.py
amapy_contents/docker_content.py
amapy_contents/file_stat.py
amapy_contents/posix_content.py
amapy_contents/url_content.py
amapy_contents/tests/__init__.py
amapy_contents/tests/test_blobstore_content.py
amapy_contents/tests/test_content.py
amapy_contents/tests/test_content_factory.py
amapy_contents/tests/test_content_set.py
amapy_contents/tests/test_content_uoloader.py
amapy_contents/tests/test_docker_content.py
amapy_contents/tests/test_file_stat.py
amapy_contents/tests/test_posix_content.py
amapy_contents-1.0.1.dist-info/METADATA
amapy_contents-1.0.1.dist-info/WHEEL
amapy_contents-1.0.1.dist-info/top_level.txt
amapy_contents-1.0.1.dist-info/RECORD
