Metadata-Version: 2.1
Name: amapy-contents
Version: 1.0.1
Summary: The Contents plugin for ama project.
License: Copyright (c) 2024 Roche Diagnostics Computation Science & Informatics
Requires-Python: <3.11,>=3.10
Requires-Dist: aiohttp<4.0.0,>=3.3.0
Requires-Dist: amapy-db==1.*
Requires-Dist: amapy-pluggy==1.*
Requires-Dist: amapy-utils==1.*
Requires-Dist: backoff==2.2.*
